signal_filters/__init__.py
signal_filters/filters.py
signal_filters/utils.py
SignalFilters-0.0.8.dist-info/LICENSE.txt
SignalFilters-0.0.8.dist-info/METADATA
SignalFilters-0.0.8.dist-info/WHEEL
SignalFilters-0.0.8.dist-info/top_level.txt
SignalFilters-0.0.8.dist-info/RECORD
