Metadata-Version: 2.1
Name: SignalFilters
Version: 0.0.8
Summary: Filtering digital signals using a front end to scipy filters
Home-page: https://github.com/eelcovv/SignalFilters
Author: Eelco van Vliet
Author-email: eelcovv@gmail.nl
License: MIT
Project-URL: Documentation, https://signalfilters.readthedocs.io/en/latest/
Platform: any
Classifier: Development Status :: 4 - Beta
Classifier: Programming Language :: Python
License-File: LICENSE.txt
Requires-Dist: numpy
Requires-Dist: pandas
Requires-Dist: PeakUtils
Requires-Dist: scipy
Requires-Dist: importlib-metadata ; python_version < "3.8"
Provides-Extra: dev
Requires-Dist: setuptools ; extra == 'dev'
Requires-Dist: tabulate ; extra == 'dev'
Requires-Dist: pre-commit ; extra == 'dev'
Requires-Dist: black ; extra == 'dev'
Requires-Dist: pytest ; extra == 'dev'
Requires-Dist: pytest-cov ; extra == 'dev'
Requires-Dist: tox ; extra == 'dev'
Provides-Extra: examples
Requires-Dist: funcy ; extra == 'examples'
Requires-Dist: seaborn ; extra == 'examples'
Requires-Dist: matplotlib ; extra == 'examples'
Requires-Dist: tabulate ; extra == 'examples'
Requires-Dist: pymdfreader ; extra == 'examples'
Provides-Extra: notebook
Requires-Dist: jupyter ; extra == 'notebook'
Requires-Dist: funcy ; extra == 'notebook'
Requires-Dist: seaborn ; extra == 'notebook'
Requires-Dist: matplotlib ; extra == 'notebook'
Requires-Dist: tabulate ; extra == 'notebook'
Requires-Dist: pymdfreader ; extra == 'notebook'
Provides-Extra: testing
Requires-Dist: setuptools ; extra == 'testing'
Requires-Dist: pytest ; extra == 'testing'
Requires-Dist: pytest-cov ; extra == 'testing'
